AS_Python_Packaging/AS_Packaging.py
AS_Python_Packaging/__init__.py
OTT_AS-0.1.dist-info/License.txt
OTT_AS-0.1.dist-info/METADATA
OTT_AS-0.1.dist-info/WHEEL
OTT_AS-0.1.dist-info/top_level.txt
OTT_AS-0.1.dist-info/RECORD
