Metadata-Version: 2.1
Name: OTT-AS
Version: 0.1
Summary: StreamSights OTT Platform User Class 
Author: Parth
Author-email: mohrilparth@gmail.com
License: MIT
License-File: License.txt
